anacalc/__init__.py
anacalc-0.0.1.dist-info/METADATA
anacalc-0.0.1.dist-info/WHEEL
anacalc-0.0.1.dist-info/top_level.txt
anacalc-0.0.1.dist-info/RECORD
